amrita/API.py
amrita/__init__.py
amrita/__main__.py
amrita/bot.py
amrita/cli.py
amrita/config.py
amrita/config_manager.py
amrita/load_test.py
amrita/resource.py
amrita/cmds/main.py
amrita/cmds/plugin.py
amrita/plugins/chat/API.py
amrita/plugins/chat/__init__.py
amrita/plugins/chat/builtin_hook.py
amrita/plugins/chat/chatmanager.py
amrita/plugins/chat/check_rule.py
amrita/plugins/chat/config.py
amrita/plugins/chat/event.py
amrita/plugins/chat/exception.py
amrita/plugins/chat/hook_manager.py
amrita/plugins/chat/matcher.py
amrita/plugins/chat/matcher_manager.py
amrita/plugins/chat/on_event.py
amrita/plugins/chat/page.py
amrita/plugins/chat/preprocess.py
amrita/plugins/chat/handlers/add_notices.py
amrita/plugins/chat/handlers/chat.py
amrita/plugins/chat/handlers/choose_prompt.py
amrita/plugins/chat/handlers/debug_switchs.py
amrita/plugins/chat/handlers/del_memory.py
amrita/plugins/chat/handlers/disable.py
amrita/plugins/chat/handlers/enable.py
amrita/plugins/chat/handlers/fakepeople_switch.py
amrita/plugins/chat/handlers/insights.py
amrita/plugins/chat/handlers/mcp.py
amrita/plugins/chat/handlers/poke_event.py
amrita/plugins/chat/handlers/preset_test.py
amrita/plugins/chat/handlers/presets.py
amrita/plugins/chat/handlers/prompt.py
amrita/plugins/chat/handlers/recall.py
amrita/plugins/chat/handlers/sessions.py
amrita/plugins/chat/handlers/set_preset.py
amrita/plugins/chat/migrations/1d99948099bb_fix_memory.py
amrita/plugins/chat/migrations/25b14ed0ad3c_insights.py
amrita/plugins/chat/migrations/3537b7cb6a29_init.py
amrita/plugins/chat/migrations/5740c5aae763_json.py
amrita/plugins/chat/migrations/ec1f1e46989b_usage.py
amrita/plugins/chat/templates/function.html
amrita/plugins/chat/templates/models.html
amrita/plugins/chat/utils/admin.py
amrita/plugins/chat/utils/event.py
amrita/plugins/chat/utils/functions.py
amrita/plugins/chat/utils/libchat.py
amrita/plugins/chat/utils/lock.py
amrita/plugins/chat/utils/memory.py
amrita/plugins/chat/utils/models.py
minichatagent-0.5.0.dist-info/licenses/LICENSE
minichatagent-0.5.0.dist-info/METADATA
minichatagent-0.5.0.dist-info/WHEEL
minichatagent-0.5.0.dist-info/entry_points.txt
minichatagent-0.5.0.dist-info/top_level.txt
minichatagent-0.5.0.dist-info/RECORD
