Metadata-Version: 2.4
Name: minichatagent
Version: 0.5.0
Summary: MiniChatAgent: an AI bot framework powered by NoneBot2 (based on Amrita)
License-Expression: AGPL-3.0-or-later
Project-URL: Homepage, https://github.com/momo-mnsjtxy/MiniAgent
Project-URL: Source, https://github.com/momo-mnsjtxy/MiniAgent
Project-URL: Issue Tracker, https://github.com/momo-mnsjtxy/MiniAgent/issues
Project-URL: Upstream, https://github.com/LiteSuggarDEV/Amrita
Requires-Python: <4.0,>=3.10
License-File: LICENSE
Requires-Dist: tomli>=2.0.0
Requires-Dist: tomli-w>=1.0.0
Requires-Dist: click>=8.2.1
Requires-Dist: colorama>=0.4
Requires-Dist: toml>=0.10.2
Requires-Dist: pip>=25.2
Requires-Dist: nb-cli>=1.0.0
Requires-Dist: nonebot-plugin-localstore>=0.7.4
Requires-Dist: typing-extensions>=4.6.0
Requires-Dist: uv>=0.8.12
Requires-Dist: requests>=2.0
Requires-Dist: python-multipart>=0.0.20
Requires-Dist: aiofiles>=24.1.0
Requires-Dist: packaging>=25.0
Requires-Dist: zipp>=3.23.0
Requires-Dist: pytz>=2025.2
Provides-Extra: full
Requires-Dist: aiohttp>=3.13.2; extra == "full"
Requires-Dist: pillow>=12.0.0; extra == "full"
Requires-Dist: fastmcp>=2.13.0.2; extra == "full"
Requires-Dist: bcrypt>=4.3.0; extra == "full"
Requires-Dist: async-lru>=2.0.5; extra == "full"
Requires-Dist: jinja2>=3.1.6; extra == "full"
Requires-Dist: uvicorn>=0.35.0; extra == "full"
Requires-Dist: psutil>=7.0.0; extra == "full"
Requires-Dist: pytz>=2025.1; extra == "full"
Requires-Dist: stubs>=1.0.0; extra == "full"
Requires-Dist: dotenv>=0.9.9; extra == "full"
Requires-Dist: importlib>=1.0.4; extra == "full"
Requires-Dist: watchfiles<1.0.0; extra == "full"
Requires-Dist: openai<=1.99.0,>=1.66.3; extra == "full"
Requires-Dist: pydantic>=2.4.2; extra == "full"
Requires-Dist: jieba>=0.42.1; extra == "full"
Requires-Dist: nonebot-plugin-orm[default]>=0.8.2; extra == "full"
Requires-Dist: nonebot-adapter-onebot>=2.4.6; extra == "full"
Requires-Dist: nonebot2[fastapi]>=2.4.3; extra == "full"
Dynamic: license-file
